{"assets/doga.jpeg":["assets/doga.jpeg"],"assets/doga2.png":["assets/doga2.png"],"assets/earth.jpeg":["assets/earth.jpeg"],"assets/earth.png":["assets/earth.png"],"assets/jupiter.jpeg":["assets/jupiter.jpeg"],"assets/jupiter_barycenter.png":["assets/jupiter_barycenter.png"],"assets/mars.jpeg":["assets/mars.jpeg"],"assets/mars.png":["assets/mars.png"],"assets/mercury.jpeg":["assets/mercury.jpeg"],"assets/mercury.png":["assets/mercury.png"],"assets/moon.jpeg":["assets/moon.jpeg"],"assets/moon.png":["assets/moon.png"],"assets/neptune.jpeg":["assets/neptune.jpeg"],"assets/neptune_barycenter.png":["assets/neptune_barycenter.png"],"assets/pluto.jpeg":["assets/pluto.jpeg"],"assets/pluto.png":["assets/pluto.png"],"assets/polaris.png":["assets/polaris.png"],"assets/pusula.png":["assets/pusula.png"],"assets/saturn.jpeg":["assets/saturn.jpeg"],"assets/saturn_barycenter.png":["assets/saturn_barycenter.png"],"assets/sun.jpeg":["assets/sun.jpeg"],"assets/sun.png":["assets/sun.png"],"assets/teleskop.jpeg":["assets/teleskop.jpeg"],"assets/uranus.jpeg":["assets/uranus.jpeg"],"assets/uranus_barycenter.png":["assets/uranus_barycenter.png"],"assets/uzay.jpeg":["assets/uzay.jpeg"],"assets/uzay2.png":["assets/uzay2.png"],"assets/venus.jpeg":["assets/venus.jpeg"],"assets/venus.png":["assets/venus.png"],"packages/cupertino_icons/assets/CupertinoIcons.ttf":["packages/cupertino_icons/assets/CupertinoIcons.ttf"]}